{
    "file_path": "C:/Dev/squad-ai/CodeSharpDoc/inputs/code_files_generated/Studi.Api.Lms.User/ResponseModel/PublicInfoResponseModel.cs",
    "index_shift_code": 47,
    "struct_type": "Class",
    "namespace_name": "",
    "usings": [],
    "access_modifier": "public",
    "struct_name": "PublicInfoResponseModel",
    "base_class_name": "",
    "interfaces_names": [],
    "related_structures": [],
    "methods": [],
    "properties": [
        {
            "name": "Pseudo",
            "prop_name": "Pseudo",
            "prop_type": "string",
            "is_property": true,
            "is_field": false
        },
        {
            "name": "Civility",
            "prop_name": "Civility",
            "prop_type": "string?",
            "is_property": true,
            "is_field": false
        },
        {
            "name": "FirstName",
            "prop_name": "FirstName",
            "prop_type": "string",
            "is_property": true,
            "is_field": false
        },
        {
            "name": "LastName",
            "prop_name": "LastName",
            "prop_type": "string",
            "is_property": true,
            "is_field": false
        },
        {
            "name": "BirthName",
            "prop_name": "BirthName",
            "prop_type": "string?",
            "is_property": true,
            "is_field": false
        },
        {
            "name": "AboutMe",
            "prop_name": "AboutMe",
            "prop_type": "string?",
            "is_property": true,
            "is_field": false
        },
        {
            "name": "LinkedInUrl",
            "prop_name": "LinkedInUrl",
            "prop_type": "string?",
            "is_property": true,
            "is_field": false
        },
        {
            "name": "DoesAppearInRanking",
            "prop_name": "DoesAppearInRanking",
            "prop_type": "bool?",
            "is_property": true,
            "is_field": false
        },
        {
            "name": "DoesAppearInLearnerDirectory",
            "prop_name": "DoesAppearInLearnerDirectory",
            "prop_type": "bool?",
            "is_property": true,
            "is_field": false
        },
        {
            "name": "IsOpenToCollaboration",
            "prop_name": "IsOpenToCollaboration",
            "prop_type": "bool?",
            "is_property": true,
            "is_field": false
        },
        {
            "name": "ProfilePictureUrl",
            "prop_name": "ProfilePictureUrl",
            "prop_type": "Uri",
            "is_property": true,
            "is_field": false
        },
        {
            "name": "BackgroundPictureUrl",
            "prop_name": "BackgroundPictureUrl",
            "prop_type": "Uri",
            "is_property": true,
            "is_field": false
        },
        {
            "name": "ProfessionalExperiences",
            "prop_name": "ProfessionalExperiences",
            "prop_type": "IEnumerable<ProfessionalExperienceResponseModel>",
            "is_property": true,
            "is_field": false
        },
        {
            "name": "Trainings",
            "prop_name": "Trainings",
            "prop_type": "IEnumerable<TrainingResponseModel>",
            "is_property": true,
            "is_field": false
        },
        {
            "name": "Scores",
            "prop_name": "Scores",
            "prop_type": "UserScoresResponseModel?",
            "is_property": true,
            "is_field": false
        },
        {
            "name": "Study",
            "prop_name": "Study",
            "prop_type": "StudyInfoResponseModel?",
            "is_property": true,
            "is_field": false
        }
    ],
    "name": "PublicInfoResponseModel"
}