{
    "title": "D\u00e9velopper une solution digitale avec Java",
    "academic_level": "Bac+3",
    "header-training": "\u2022 Code - IT D\u00e9veloppement D\u00e9velopper une solution digitale avec Java Bac+3 Eligible CPF En partenariat acad\u00e9mique avec Recevoir la brochure 100% en ligne 24h/24 et 7j/7 \u2022 Web & Mobile Dur\u00e9e estim\u00e9e 200h \u2022 4 mois D\u00e9marrage A tout moment de l'ann\u00e9e Certification Bloc de comp\u00e9tences\n               \u2022 \n                Niveau 6 (Bac+3)\n",
    "bref": "\u2022 Programmez et d\u00e9veloppez une solution digitale avec Java ! Le concepteur d\u00e9veloppeur de solutions digitales exerce dans une multitude de secteurs, ses missions principales consistent \u00e0 l\u2019identification et l\u2019analyse des besoins permettant de concevoir et de d\u00e9ployer les solutions digitales, tout en effectuant la maintenance et le suivi des op\u00e9rations afin de d\u00e9velopper ou valoriser l\u2019activit\u00e9 d\u2019une organisation. Cette formation se concentre sur la phase de d\u00e9veloppement de la solution digitale : de la programmation jusqu\u2019\u00e0 l\u2019am\u00e9lioration continue de la solution , vous ma\u00eetriserez de A \u00e0 Z les \u00e9tapes cl\u00e9s pour d\u00e9velopper une solution digitale avec Java. Vous serez capable de : D\u00e9velopper une application Web avec Java Cr\u00e9er un site web avec HTML, CSS et le Framework Bootstrap D\u00e9velopper des sites web dynamiques avec PHP\n",
    "programme": "\u2022 Piloter la production de contenus digitaux\n    \u25e6 Introduction \u00e0 la production de contenus digitaux\n    \u25e6 La cr\u00e9ation de contenu digital en ad\u00e9quation avec sa cible\n    \u25e6 L'orientation artistique et le brief cr\u00e9atif\n    \u25e6 La gestion de la production de contenus digitaux\n    \u25e6 La mise en place op\u00e9rationnelle de sa strat\u00e9gie de production de contenus\n    \u25e6 La proposition de production de contenu\n    \u25e6 Le workflow\n\u2022 Cr\u00e9er un site web avec HTML, CSS et le Framework Bootstrap\n    \u25e6 Introduction au HTML\n    \u25e6 Syntaxe g\u00e9n\u00e9rale de HTML\n    \u25e6 L'organisation du texte\n    \u25e6 Un langage hypertexte\n    \u25e6 Le multim\u00e9dia en HTML\n    \u25e6 Introduction au CSS\n    \u25e6 CSS3 : Le stylage du texte\n    \u25e6 La structuration logique en HTML5 et le mod\u00e8le de bo\u00eetes en CSS3\n    \u25e6 Les s\u00e9lecteurs CSS\n    \u25e6 La mise en page avec CSS\n    \u25e6 La cr\u00e9ation de tableaux\n    \u25e6 La cr\u00e9ation de formulaires\n    \u25e6 Layout avec CSS Grid\n    \u25e6 Les effets avanc\u00e9s de CSS\n    \u25e6 Utiliser des documentations CSS\n    \u25e6 Le responsive design\n    \u25e6 Valider la qualit\u00e9 de son site\n    \u25e6 L'installation et la prise en main du framework Bootstrap : Hello world\n    \u25e6 La grille bootstrap\n    \u25e6 Les \u00e9l\u00e9ments bootstrap\n    \u25e6 Les composants bootstrap\n    \u25e6 Ouverture vers d'autres framework CSS\n    \u25e6 SASS\n    \u25e6 Le r\u00e9f\u00e9rencement des sites Web\n    \u25e6 D\u00e9ployer son site sur le Web\n\u2022 Dynamiser vos sites web avec Javascript\n    \u25e6 Initiation aux objets et aux classes\n    \u25e6 L'API DOM\n    \u25e6 La programmation \u00e9v\u00e9nementielle en Javascript\n    \u25e6 Les formulaires HTML et Javascript (entr\u00e9es / sorties)\n    \u25e6 Pr\u00e9sentation de la librairie JQuery\n    \u25e6 Les bases de JQuery\n    \u25e6 L'utilisation de JSON\n    \u25e6 La programmation AJAX\n    \u25e6 Les promesses et l'API Fetch\n    \u25e6 L'API Canvas en Javascript\n\u2022 D\u00e9velopper des sites web dynamiques avec PHP\n    \u25e6 PHP et HTML (sorties)\n    \u25e6 Les types de donn\u00e9es, les variables et les constantes\n    \u25e6 Les op\u00e9rateurs de comparaison et les expressions bool\u00e9ennes\n    \u25e6 Les fonctions\n    \u25e6 Les tableaux\n    \u25e6 Les conditions\n    \u25e6 Les boucles\n    \u25e6 Cr\u00e9er ses propres fonctions\n    \u25e6 L'organisation des fichiers PHP\n    \u25e6 Les superglobales Get, Post et Files\n    \u25e6 Les superglobables Server, Env et Session\n    \u25e6 La s\u00e9curit\u00e9\n    \u25e6 La manipulation des dates\n    \u25e6 La manipulation des fichiers en PHP\n    \u25e6 Les expressions r\u00e9guli\u00e8res\n    \u25e6 Utiliser la documentation PHP et Standard de codage PHP\n    \u25e6 La pr\u00e9paration de l'environnement de travail\n    \u25e6 La programmation Orient\u00e9e Objet : concepts de base\n    \u25e6 La programmation Orient\u00e9e Objet : concepts avanc\u00e9s\n    \u25e6 La gestion des erreurs\n    \u25e6 La programmation Orient\u00e9e Objet : Design Patterns\n    \u25e6 La programmation Orient\u00e9e Objet : L\u2019encapsulation et la visibilit\u00e9\n    \u25e6 Le mod\u00e8le MVC\n\u2022 Cr\u00e9er et administrer une base de donn\u00e9es relationnelle\n    \u25e6 Introduction g\u00e9n\u00e9rale aux bases de donn\u00e9es, notion de SGBDR\n    \u25e6 Mod\u00e8le conceptuel de donn\u00e9es et mod\u00e8le logique de donn\u00e9es\n    \u25e6 Les diagrammes fonctionnels\n    \u25e6 Le diagramme de classe\n    \u25e6 Introduction au passage UML-Relationnel\n    \u25e6 Cr\u00e9ation et alimentation de bases de donn\u00e9es SQL\n    \u25e6 L'interrogation de bases de donn\u00e9es SQL\n    \u25e6 D\u00e9couvrir un autre SGBDR : PostgreSQL\n    \u25e6 Connexion \u00e0 la base de donn\u00e9es en PHP\n    \u25e6 PHP/PDO : acc\u00e8s en lecture/\u00e9criture\n    \u25e6 Les requ\u00eates SQL\n    \u25e6 Les fonctions SQL\n    \u25e6 Les jointures SQL\n    \u25e6 G\u00e9rer les acc\u00e8s des utilisateurs au niveau PHP et BD\n    \u25e6 D\u00e9couverte d'un ORM PHP\n    \u25e6 Projet : Cr\u00e9er et administrer une base de donn\u00e9es\n    \u25e6 Introduction NOSQL\n    \u25e6 Introduction \u00e0 MongoDB\n\u2022 Cr\u00e9er et administrer une base de donn\u00e9es non relationnelle\n    \u25e6 Introduction NOSQL\n    \u25e6 Introduction \u00e0 MongoDB\n\u2022 D\u00e9velopper une application Web avec Java\n    \u25e6 Introduction au JAVA\n    \u25e6 Les types primitifs\n    \u25e6 Les common objects\n    \u25e6 Le instructions conditionnelles\n    \u25e6 Les m\u00e9thodes\n    \u25e6 Les exceptions\n    \u25e6 Les classes - construction\n    \u25e6 Les classes - Types de classes\n    \u25e6 Les classes - Utilisation dans un contexte POO\n    \u25e6 Les autres sp\u00e9cificit\u00e9s d'une classe java\n    \u25e6 Les collections\n    \u25e6 La manipulation des dates\n    \u25e6 Les patrons de conception (design patterns)\n    \u25e6 Les fonctions anonymes et leurs utilisations\n    \u25e6 L'outil Maven - pr\u00e9sentation\n    \u25e6 L'outil Maven - son utilisation\n    \u25e6 L'outil Maven - Automatisation avec Jenkins\n    \u25e6 La librairie Spring - ses principes\n    \u25e6 La librairie Spring - springboot\n    \u25e6 La librairie Spring - Son utilisation avec une API\n    \u25e6 Les traces (log)\n    \u25e6 Le standard openAPI / Swagger - Sa mise en place sur une API\n    \u25e6 Les m\u00e9thodes de d\u00e9veloppement\n    \u25e6 Les Tests unitaires / d'int\u00e9gration avec JUnit / Mockito\n    \u25e6 Les tests d'int\u00e9gration d'une fonctionnalit\u00e9 avec cucumber\n    \u25e6 Les outils d\u2019aide aux bonnes pratiques de d\u00e9veloppement\n    \u25e6 Les BDD H2 et Lombrok\n    \u25e6 La persistance de donn\u00e9es (DATA JDBC/JCPA)\n    \u25e6 La pr\u00e9sentation de l'OWASP et du TOP10 des failles de s\u00e9curit\u00e9\n    \u25e6 La mise en place d'une fonction d'authentification\n    \u25e6 La v\u00e9rification d'authentification sur une API\n    \u25e6 La mise en place d'une fonction d'autorisation (par r\u00f4le)\n    \u25e6 La v\u00e9rification d'authentification et d'autorisation sur une API\n\u2022 D\u00e9velopper \u00a0une application mobile avec React Native\n    \u25e6 Le d\u00e9veloppement Mobile\n    \u25e6 Introduction \u00e0 React Native : l'outil Expo\n    \u25e6 Les bases de React Native\n    \u25e6 Les composants React Native\n    \u25e6 Les props et les states\n    \u25e6 Style et mise en page avec Flexbox\n    \u25e6 Du code diff\u00e9rent en fonction de la plateforme\n    \u25e6 L'utilisation de Redux\n    \u25e6 Les extensions de Redux\n    \u25e6 L'organisation d'une application React Native\n    \u25e6 La navigation avec React Native\n    \u25e6 Les diff\u00e9rents types de navigators\n    \u25e6 L'animation avec React Native\n    \u25e6 Installer les \u00e9mulateurs\n    \u25e6 Utiliser une base donn\u00e9es locale : SQLITE\n    \u25e6 Les APIs React Native et modules natifs\n    \u25e6 Le debugging\n    \u25e6 Le d\u00e9ploiement d'une application sur les stores\n    \u25e6 Cr\u00e9er une application React Native sans Expo\n    \u25e6 Projet - d\u00e9velopper \u00a0une application mobile avec React Native\n\u2022 Concevoir une API\n    \u25e6 Pr\u00e9sentation des API\n    \u25e6 Concevoir une API\n    \u25e6 G\u00e9rer les acc\u00e8s \u00e0 une API\n\u2022 Utiliser des API\n    \u25e6 Les API d'authentification (OAuth, ..)\n    \u25e6 Les API Google / AWS\n    \u25e6 Les API de paiement\n\u2022 Utiliser un outil de gestion de version de code source\n    \u25e6 Introduction \u00e0 la ligne de commande\n    \u25e6 Introduction \u00e0 Git et Github\n    \u25e6 Les bases\n    \u25e6 Les interactions avec le d\u00e9p\u00f4t distant\n    \u25e6 Naviguer dans l'historique\n    \u25e6 La gestion des branches\n    \u25e6 Les branches avec Git - Rebaser\n    \u25e6 Les bonnes pratiques\n    \u25e6 Projet - Utiliser Git et Github pour g\u00e9rer son code source\n    \u25e6 Introduction \u00e0 Gitlab\n\u2022 Maintenir et documenter son projet\n    \u25e6 La documentation de l'architecture et du code\n    \u25e6 Am\u00e9liorer sa solution\n    \u25e6 La documentation pour l'utilisateur\n    \u25e6 Le pentest\n    \u25e6 Gestion de la dette technique\n",
    "cards-diploma": "\u2022 \u00c0 l\u2019issue de la formation, vous obtiendrez Attestation reconnaissant l'acquisition d'un bloc de comp\u00e9tences Obtenez le Bloc de comp\u00e9tences \"D\u00e9velopper une solution digitale\" issu du Titre RNCP \u201cConcepteur d\u00e9veloppeur de solutions digitales\u201d de HETIC, niveau 6 enregistr\u00e9 au RNCP sous le num\u00e9ro RNCP 36146 par d\u00e9cision de France Comp\u00e9tences du 26/01/2022 Attestation de fin de formation \u00e9cole en partenariat avec Hetic & Voir le specimen\n",
    "methode": "\u2022 La m\u00e9thode Studi : votre chemin vers le succ\u00e8s Accompagnement jusqu\u2019\u00e0 la r\u00e9ussite Support p\u00e9dagogique \u00e0 chaque \u00e9tape de votre parcours de formation, et assistance de vos formateurs experts sous 24h ouvr\u00e9es maximum Coaching carri\u00e8re Programme de coaching exclusif orient\u00e9 emploi et carri\u00e8re pour booster votre employabilit\u00e9 et votre succ\u00e8s en poste Apprendre en faisant P\u00e9dagogie active o\u00f9 l\u2019apprenant est acteur de son propre apprentissage : construisez, cr\u00e9ez, exp\u00e9rimentez ! Se pr\u00e9parer pour le monde r\u00e9el Apprentissage directement applicable bas\u00e9 sur des exemples r\u00e9els, projets, cas pratiques et contenus immersifs R\u00e9seau d'experts de premier plan Plus de 300 formateurs experts pour transmettre les meilleures pratiques dans chaque domaine Excellence acad\u00e9mique & digitale Cours \u00e9crits et vid\u00e9os, \u00e0 la demande et en direct Plateforme de formation accessible 24h/24 et 7j/7 en ligne et sur app iOS/Android\n",
    "modalites": "\u2022 Conditions d'admission\n    \u25e6 Avoir valid\u00e9 un dipl\u00f4me ou un Titre certifi\u00e9 de niveau 5 (Bac+2) dans le domaine du d\u00e9veloppement\n    \u25e6 Avoir valid\u00e9 un dipl\u00f4me ou un Titre certifi\u00e9 de niveau 5 (Bac+2) ou avoir valid\u00e9 120 cr\u00e9dits ECTS, et justifier d\u2019une exp\u00e9rience professionnelle de 12 mois minimum dans le domaine du d\u00e9veloppement\n    \u25e6 Avoir valid\u00e9 un dipl\u00f4me ou un Titre certifi\u00e9 de niveau 4 (Bac)+avoir valid\u00e9 une ann\u00e9e d\u2019\u00e9tude (60 ECTS) et justifier d\u2019une exp\u00e9rience professionnelle de 24 mois minimum dans le domaine du d\u00e9veloppement\n    \u25e6 Avoir valid\u00e9 un dipl\u00f4me ou un Titre certifi\u00e9 de niveau 4 (Bac) et justifier d\u2019une exp\u00e9rience professionnelle de 36 mois minimum dans le domaine du d\u00e9veloppement\n    \u25e6 Pour entrer en formation pr\u00e9parant au Titre vis\u00e9, le candidat doit :\n    \u25e6 OU\n    \u25e6 Pour toute autre situation, contactez un conseiller en formation qui \u00e9tudiera votre profil pour \u00e9tudier votre admissibilit\u00e9.\n\u2022 Examen\n    \u25e6 Mois d'examen : Juin, D\u00e9cembre\n    \u25e6 Lieu : En ligne\n    \u25e6 Avoir valid\u00e9 (r\u00e9ussi) l\u2019\u00e9preuve d\u2019examen du bloc de comp\u00e9tences.\n    \u25e6 Pour obtenir le Titre, le candidat sera \u00e9valu\u00e9 selon les modalit\u00e9s suivantes :\n    \u25e6 Nature des \u00e9preuves : 1 projet professionnel et une vid\u00e9o de pr\u00e9sentation du projet \u00e0 produire\n\u2022 Certification\n    \u25e6 Pour obtenir le taux d\u2019insertion dans les fonctions vis\u00e9es,consulter la fiche RNCP sur le site de France comp\u00e9tences\n\u2022 Equivalences et passerelles\n    \u25e6 Si vous pensez pouvoir b\u00e9n\u00e9ficier d'une \u00e9quivalence de bloc sur un Dipl\u00f4me ou Titre d'un niveau et d'une sp\u00e9cialit\u00e9 similaire acquis pr\u00e9c\u00e9demment, vous pouvez nous contacter pour l'\u00e9tude d'une \u00e9quivalence totale ou partielle.\n\u2022 Poursuite d'\u00e9tudes\n    \u25e6 Apr\u00e8s avoir obtenu le bloc de comp\u00e9tences, il est possible de poursuivre sur l'obtention du Titre complet.\n",
    "financement": "\u2022 Tarifs et solutions de financement Voir tout Financement CPF France Travail Bourse d'\u00e9tudes Financement personnel 1 690 \u20ac Tarif pour les particuliers. Financement CPF Mon compte CPF Financement jusqu'\u00e0 100% France Travail Formation \u00e9ligible \u00e0 des aides France Travail Financement jusqu'\u00e0 100% Bourse d'\u00e9tudes B\u00e9n\u00e9ficiez d\u2019une bourse d\u2019\u00e9tude en fonction de votre profil. Jusqu'\u00e0 -30% Financement personnel Maitrisez le co\u00fbt de votre formation en la finan\u00e7ant sur 10, 12, 24 ou 36 mois **** . A partir de 69\u20ac / mois Inclus Cours \u00e9crits et vid\u00e9os \u00e0 la demande Acc\u00e8s illimit\u00e9 aux 4 000 cours du soir* en direct et replay Accompagnement p\u00e9dagogique personnalis\u00e9 Projets professionnels Coaching carri\u00e8re Acc\u00e8s illimit\u00e9 \u00e0 Studi + pendant 2 ans Frais de dossier et d'inscription** Garantie R\u00e9ussite 2 ans et Garantie Dipl\u00f4m\u00e9 ou Rembours\u00e9*** *Nombre moyen de cours du soir en direct observ\u00e9s sur les 12 derniers mois (organis\u00e9s majoritairement\u00a0\u00e0 partir de 18h) **Hors Dipl\u00f4mes d\u2019\u00c9tat\u00a0et pr\u00e9paration aux concours ***Voir les CGV Studi ****\u00a0Sous re\u0301serve d\u2019acceptation. Vous disposez d\u2019un de\u0301lai de re\u0301tractation. Voir conditions\n",
    "simulation": "\u2022 Je simule la dur\u00e9e de ma formation 9 heures / semaine \u2022 Total : 200 h Formation termin\u00e9e : mars 2025 Examen : juin 2025 Le d\u00e9lai moyen d'acc\u00e8s \u00e0 la plateforme est de 14 jours. Ce d\u00e9lai peut varier en fonction du type de financement et de l'accord du financeur. Une fois l'accord de votre financeur re\u00e7u, vous recevrez un mail de connexion \u00e0 la plateforme. Vous cliquez sur le lien, choisissez votre mot de passe et d\u00e9marrez votre formation.\n",
    "url": "https://www.studi.com/fr/formation/developpement/developper-une-solution-digitale-avec-java"
}